_version.py
geouned/__init__.py
geouned/GEOReverse/CodeVersion.py
geouned/GEOReverse/__init__.py
geouned/GEOReverse/core.py
geouned/GEOReverse/Modules/MCNPinput.py
geouned/GEOReverse/Modules/Objects.py
geouned/GEOReverse/Modules/XMLParser.py
geouned/GEOReverse/Modules/XMLinput.py
geouned/GEOReverse/Modules/buildCAD.py
geouned/GEOReverse/Modules/buildSolidCell.py
geouned/GEOReverse/Modules/data_class.py
geouned/GEOReverse/Modules/options.py
geouned/GEOReverse/Modules/processInp.py
geouned/GEOReverse/Modules/remh.py
geouned/GEOReverse/Modules/splitFunction.py
geouned/GEOReverse/Modules/Parser/PartialFormatter.py
geouned/GEOReverse/Modules/Parser/parser.py
geouned/GEOReverse/Modules/Utils/BooleanSolids.py
geouned/GEOReverse/Modules/Utils/__init__.py
geouned/GEOReverse/Modules/Utils/booleanFunction.py
geouned/GEOReverse/Modules/Utils/boundBox.py
geouned/GEOReverse/scripts/__init__.py
geouned/GEOReverse/scripts/geouned_csgtocad.py
geouned/GEOUNED/__init__.py
geouned/GEOUNED/code_version.py
geouned/GEOUNED/core.py
geouned/GEOUNED/conversion/__init__.py
geouned/GEOUNED/conversion/cell_definition.py
geouned/GEOUNED/cuboid/__init__.py
geouned/GEOUNED/cuboid/translate.py
geouned/GEOUNED/decompose/__init__.py
geouned/GEOUNED/decompose/decom_one.py
geouned/GEOUNED/loadfile/__init__.py
geouned/GEOUNED/loadfile/load_functions.py
geouned/GEOUNED/loadfile/load_step.py
geouned/GEOUNED/scripts/__init__.py
geouned/GEOUNED/scripts/geouned_cadtocsg.py
geouned/GEOUNED/utils/__init__.py
geouned/GEOUNED/utils/basic_functions_part1.py
geouned/GEOUNED/utils/basic_functions_part2.py
geouned/GEOUNED/utils/boolean_function.py
geouned/GEOUNED/utils/boolean_solids.py
geouned/GEOUNED/utils/data_classes.py
geouned/GEOUNED/utils/functions.py
geouned/GEOUNED/utils/geometry_gu.py
geouned/GEOUNED/utils/log_utils.py
geouned/GEOUNED/utils/q_form.py
geouned/GEOUNED/void/__init__.py
geouned/GEOUNED/void/void.py
geouned/GEOUNED/void/void_box_class.py
geouned/GEOUNED/void/void_functions.py
geouned-1.6.0.dist-info/licenses/LICENSE.txt
geouned-1.6.0.dist-info/METADATA
geouned-1.6.0.dist-info/WHEEL
geouned-1.6.0.dist-info/entry_points.txt
geouned-1.6.0.dist-info/top_level.txt
geouned-1.6.0.dist-info/RECORD
