Metadata-Version: 2.4
Name: geouned
Version: 1.6.0
Summary: Conversion tool from CAD to CGS/CGS to CAD for Monte Carlo particle transport codes (OpenMC, Phits, Serpent, MCNP)
Author-email: Juan-Pablo Catalan <jpcatalan@ind.uned.es>, Patrick Sauvan <psauvan@ind.uned.es>
Maintainer-email: Patrick Sauvan <psauvan@ind.uned.es>, Juan-Pablo Catalan <jpcatalan@ind.uned.es>, Juan Garcia <jgarcia@ind.uned.es>, Francisco Ogando <fogando@ind.uned.es>, Javier Alguacil <jalguacil@ind.uned.es>
License:                       EUROPEAN UNION PUBLIC LICENCE v. 1.2
Project-URL: Homepage, https://github.com/GEOUNED-org
Project-URL: Repository, https://github.com/GEOUNED-org/GEOUNED
Project-URL: Documentation, https://geouned-org.github.io/GEOUNED/index.html
Keywords: csg,cad,openmc,serpent,phits,mcnp,geometry
Classifier: Programming Language :: Python :: 3
Classifier: License :: OSI Approved :: European Union Public Licence 1.2 (EUPL 1.2)
Classifier: Operating System :: OS Independent
Requires-Python: >=3.8
License-File: LICENSE.txt
Requires-Dist: tqdm
Requires-Dist: numpy
Provides-Extra: tests
Requires-Dist: pytest; extra == "tests"
Requires-Dist: black==24.4.2; extra == "tests"
Provides-Extra: docs
Requires-Dist: sphinx; extra == "docs"
Requires-Dist: pydata-sphinx-theme; extra == "docs"
Requires-Dist: sphinx_autodoc_typehints; extra == "docs"
Dynamic: license-file
